MANIFEST.in
README.rst
readme.rst
setup.py
jsinclude/__init__.py
jsinclude/models.py
jsinclude.egg-info/PKG-INFO
jsinclude.egg-info/SOURCES.txt
jsinclude.egg-info/dependency_links.txt
jsinclude.egg-info/not-zip-safe
jsinclude.egg-info/requires.txt
jsinclude.egg-info/top_level.txt
jsinclude/templates/wrap.html
jsinclude/templatetags/__init__.py
jsinclude/templatetags/jsinclude.py
jsinclude/templatetags/pkg/ArgumentCollection.py
jsinclude/templatetags/pkg/ArgumentValue.py
jsinclude/templatetags/pkg/JSIError.py
jsinclude/templatetags/pkg/PathArgument.py
jsinclude/templatetags/pkg/StaticArgument.py
jsinclude/templatetags/pkg/StringValue.py
jsinclude/templatetags/pkg/TagNode.py
jsinclude/templatetags/pkg/VariableArgument.py
jsinclude/templatetags/pkg/__init__.py
jsinclude/templatetags/pkg/utils.py
jsinclude/tests/__init__.py
jsinclude/tests/argument_collection_test.py
jsinclude/tests/argument_value_test.py
jsinclude/tests/jsinclude_test.py
jsinclude/tests/path_argument_test.py
jsinclude/tests/settings.py
jsinclude/tests/static_argument_test.py
jsinclude/tests/string_value_test.py
jsinclude/tests/tagnode_construction_test.py
jsinclude/tests/tagnode_render_test.py
jsinclude/tests/utils_escapequotes_test.py
jsinclude/tests/utils_stripquotes_test.py
jsinclude/tests/variable_argument_test.py