Metadata-Version: 1.1
Name: jsinclude
Version: 1.2.3
Summary: A Django 1.3+ tag to keep JavaScript out of your templates.
Home-page: https://github.com/cobbdb/jsinclude
Author: Dan Cobb
Author-email: cobbdb@gmail.com
License: MIT
Keywords: javascript,loader,templatetag,django
Platform: UNKNOWN
Classifier: Development Status :: 5 - Production/Stable
Classifier: Intended Audience :: Developers
Classifier: License :: OSI Approved :: MIT License
Classifier: Topic :: Software Development
Classifier: Topic :: Software Development :: Libraries
Classifier: Topic :: Software Development :: Libraries :: Python Modules
Classifier: Topic :: Software Development :: Pre-processors
Classifier: Topic :: Utilities
Classifier: Operating System :: OS Independent
Classifier: Programming Language :: Python :: 2.6
Classifier: Programming Language :: Python :: 2.7
Classifier: Programming Language :: Python :: 3.3
